bframelib/__init__.py
bframelib/client.py
bframelib/interpreter.py
bframelib/bootstrap_sql/0_init.sql
bframelib/bootstrap_sql/3_column_comments.sql
bframelib/client_sql/_all_line_items.sql
bframelib/client_sql/_all_price_spans.sql
bframelib/client_sql/_local_contract_prices.sql
bframelib/client_sql/_local_contracts.sql
bframelib/client_sql/_local_customers.sql
bframelib/client_sql/_local_events.sql
bframelib/client_sql/_local_list_prices.sql
bframelib/client_sql/_local_pricebooks.sql
bframelib/client_sql/_local_products.sql
bframelib/client_sql/_product_filters.sql
bframelib/client_sql/_raw_branches.sql
bframelib/client_sql/_raw_contract_prices.sql
bframelib/client_sql/_raw_contracts.sql
bframelib/client_sql/_raw_customers.sql
bframelib/client_sql/_raw_events.sql
bframelib/client_sql/_raw_invoices.sql
bframelib/client_sql/_raw_line_items.sql
bframelib/client_sql/_raw_list_prices.sql
bframelib/client_sql/_raw_pricebooks.sql
bframelib/client_sql/_raw_products.sql
bframelib/client_sql/branches.sql
bframelib/client_sql/contract_prices.sql
bframelib/client_sql/contracts.sql
bframelib/client_sql/customers.sql
bframelib/client_sql/dates.sql
bframelib/client_sql/environments.sql
bframelib/client_sql/event_line_items.sql
bframelib/client_sql/events.sql
bframelib/client_sql/fixed_line_items.sql
bframelib/client_sql/invoices.sql
bframelib/client_sql/line_items.sql
bframelib/client_sql/list_prices.sql
bframelib/client_sql/matched_events.sql
bframelib/client_sql/organizations.sql
bframelib/client_sql/price_spans.sql
bframelib/client_sql/pricebooks.sql
bframelib/client_sql/prices.sql
bframelib/client_sql/processed_events.sql
bframelib/client_sql/products.sql
bframelib/client_sql/rated_events.sql
bframelib-0.1.21.dist-info/licenses/LICENSE
bframelib-0.1.21.dist-info/METADATA
bframelib-0.1.21.dist-info/WHEEL
bframelib-0.1.21.dist-info/top_level.txt
bframelib-0.1.21.dist-info/RECORD
