Metadata-Version: 2.4
Name: bframelib
Version: 0.1.21
Summary: An open source billing framework to generate, view and diff invoices locally.
Author-email: Allan Blair <allan@bframe.work>
License: GNU AFFERO GENERAL PUBLIC LICENSE
Project-URL: Homepage, https://bframe.work
Project-URL: Source, https://github.com/bframe-work/bframelib
Keywords: billing,invoice,invoicing,bframe
Classifier: License :: OSI Approved :: GNU Affero General Public License v3
Classifier: Programming Language :: Python
Classifier: Programming Language :: Python :: 3
Requires-Python: >=3.9
License-File: LICENSE
Requires-Dist: Jinja2>=3.0.0
Requires-Dist: duckdb>=1.0.0
Requires-Dist: sqlparse>=0.5.2
Requires-Dist: numpy>=1.20.0
Requires-Dist: pandas>=2.0.0
Provides-Extra: dev
Requires-Dist: black; extra == "dev"
Requires-Dist: isort; extra == "dev"
Requires-Dist: pip-tools; extra == "dev"
Requires-Dist: pytest; extra == "dev"
Requires-Dist: twine; extra == "dev"
Requires-Dist: build; extra == "dev"
Dynamic: license-file
